graphplotyt/__init__.py
graphplotyt/my_graphplotyt.py
graphplotyt-1.4.1.dist-info/licenses/LICENSE
graphplotyt-1.4.1.dist-info/METADATA
graphplotyt-1.4.1.dist-info/WHEEL
graphplotyt-1.4.1.dist-info/top_level.txt
graphplotyt-1.4.1.dist-info/RECORD
